benchnirs/__init__.py
benchnirs/learn.py
benchnirs/load.py
benchnirs/process.py
benchnirs/viz.py
benchnirs-1.7.1.dist-info/licenses/LICENSE
benchnirs-1.7.1.dist-info/METADATA
benchnirs-1.7.1.dist-info/WHEEL
benchnirs-1.7.1.dist-info/top_level.txt
benchnirs-1.7.1.dist-info/RECORD
