Metadata-Version: 2.4
Name: benchnirs
Version: 1.7.1
Summary: Benchmarking framework for machine learning with fNIRS
Home-page: https://gitlab.com/HanBnrd/benchnirs
Author: Johann Benerradi
Author-email: johann.benerradi@gmail.com
License: MIT
Classifier: Programming Language :: Python :: 3
Classifier: License :: OSI Approved :: MIT License
Classifier: Operating System :: OS Independent
Requires-Python: >=3.9
License-File: LICENSE
Requires-Dist: lazy_loader
Requires-Dist: tqdm
Requires-Dist: numpy<2
Requires-Dist: pandas
Requires-Dist: scipy
Requires-Dist: mne
Requires-Dist: matplotlib
Requires-Dist: seaborn
Requires-Dist: scikit-learn
Requires-Dist: torch
Requires-Dist: nirsimple
Dynamic: author
Dynamic: author-email
Dynamic: classifier
Dynamic: description
Dynamic: description-content-type
Dynamic: home-page
Dynamic: license
Dynamic: license-file
Dynamic: requires-dist
Dynamic: requires-python
Dynamic: summary
